{
  "places": [
    {
      "visits": [
        {
          "date": "23 May",
          "duration": "1100h to 1225h",
          "venues": []
        }
      ],
      "name": "Jurong Point",
      "address": "1 Jurong West Central 2",
      "lon": "103.706685012926",
      "lat": "1.33945200436319",
      "id": "648886"
    },
    {
      "visits": [
        {
          "date": "23 May",
          "duration": "1100h to 2100h",
          "venues": []
        }
      ],
      "name": "Indobowl and Royz et Vous",
      "address": "37 & 39 Sultan Gate",
      "lon": "103.860598602583",
      "lat": "1.3015049295861",
      "id": "198487"
    },
    {
      "visits": [
        {
          "date": "23 May",
          "duration": "1755h to 1830h",
          "venues": []
        }
      ],
      "name": "Changi City Point",
      "address": "5 Changi Business Park Central 1",
      "lon": "103.962792843921",
      "lat": "1.33411313029445",
      "id": "486038"
    },
    {
      "visits": [
        {
          "date": "23 May",
          "duration": "1955h to 2030h",
          "venues": [
            "FairPrice Xtra"
          ]
        }
      ],
      "name": "NEX",
      "address": "23 Serangoon Central",
      "lon": "103.871861615443",
      "lat": "1.35067552120318",
      "id": "556083"
    },
    {
      "visits": [
        {
          "date": "24 May",
          "duration": "0600h to 1500h",
          "venues": [
            "McDonald’s"
          ]
        }
      ],
      "name": "The Woodgrove",
      "address": "30 Woodlands Avenue 1",
      "lon": "103.781337285958",
      "lat": "1.42933633490183",
      "id": "739065"
    },
    {
      "visits": [
        {
          "date": "24 May",
          "duration": "1155h to 1625h",
          "venues": []
        }
      ],
      "name": "Ramada",
      "address": "16 Ah Hood Road",
      "lon": "103.846554377679",
      "lat": "1.32694504484324",
      "id": "329982"
    },
    {
      "visits": [
        {
          "date": "24 May",
          "duration": "1230h to 1300h",
          "venues": []
        }
      ],
      "name": "D'FoodStop@ABC",
      "address": "2 Jalan Bukit Merah",
      "lon": "103.80686187976",
      "lat": "1.2866292132996",
      "id": "150002"
    },
    {
      "visits": [
        {
          "date": "24 May",
          "duration": "1235h to 1310h",
          "venues": []
        }
      ],
      "name": "NTUC FairPrice",
      "address": "30 Bendemeer Road",
      "lon": "103.863880362385",
      "lat": "1.31906233206995",
      "id": "330030"
    },
    {
      "visits": [
        {
          "date": "24 May",
          "duration": "1535h to 1640h",
          "venues": [
            "Popsical"
          ]
        }
      ],
      "name": "Funan",
      "address": "107 North Bridge Road",
      "lon": "103.849984790048",
      "lat": "1.29124400604241",
      "id": "179105"
    },
    {
      "visits": [
        {
          "date": "24 May",
          "duration": "1745h to 1845h",
          "venues": []
        }
      ],
      "name": "Yew Tee Community Club",
      "address": "20 Choa Chu Kang Street 52",
      "lon": "103.744971294739",
      "lat": "1.39480564592114",
      "id": "689286"
    },
    {
      "visits": [
        {
          "date": "25 May",
          "duration": "0920h to 1000h",
          "venues": []
        },
        {
          "date": "23 May",
          "duration": "0815h to 0920h",
          "venues": []
        }
      ],
      "name": "Sheng Siong Supermarket",
      "address": "108 McNair Road",
      "lon": "103.859382719506",
      "lat": "1.3216190383169",
      "id": "321108"
    },
    {
      "visits": [
        {
          "date": "25 May",
          "duration": "1230h to 1430h",
          "venues": [
            "Beauty World Thai Massage"
          ]
        }
      ],
      "name": "Beauty World Centre",
      "address": "144 Upper Bukit Timah Road",
      "lon": "103.776539385678",
      "lat": "1.34241264188642",
      "id": "588177"
    },
    {
      "visits": [
        {
          "date": "25 May",
          "duration": "1500h to 1550h",
          "venues": [
            "Rodalink Jurong East Bicycle Megastore"
          ]
        }
      ],
      "name": "Tradehub 21",
      "address": "18 Boon Lay Way",
      "lon": "103.752749137065",
      "lat": "1.32855512493378",
      "id": "609966"
    },
    {
      "visits": [
        {
          "date": "25 May",
          "duration": "1800h to 1900h",
          "venues": []
        }
      ],
      "name": "Al Barakah Health and Beauty Mart",
      "address": "302 Woodlands Street 31",
      "lon": "103.774428425787",
      "lat": "1.43151114760044",
      "id": "730302"
    },
    {
      "visits": [
        {
          "date": "26 May",
          "duration": "0905h to 1200h",
          "venues": []
        }
      ],
      "name": "McDonald’s",
      "address": "293 Yishun Street 22",
      "lon": "103.837858420722",
      "lat": "1.43591598491658",
      "id": "760293"
    },
    {
      "visits": [
        {
          "date": "26 May",
          "duration": "1400h to 1430h",
          "venues": []
        }
      ],
      "name": "New Trendy Salon LLP",
      "address": "84 Redhill Lane",
      "lon": "103.818851050403",
      "lat": "1.28708575062296",
      "id": "150084"
    },
    {
      "visits": [
        {
          "date": "26 May",
          "duration": "1430h to 1500h",
          "venues": [
            "Passion Bike"
          ]
        }
      ],
      "name": "One Commonwealth",
      "address": "1 Commonwealth Lane",
      "lon": "103.796927634921",
      "lat": "1.30430366397836",
      "id": "149544"
    },
    {
      "visits": [
        {
          "date": "26 May",
          "duration": "1430h to 1535h",
          "venues": []
        },
        {
          "date": "26 May",
          "duration": "1320h to 1530h",
          "venues": []
        },
        {
          "date": "24 May",
          "duration": "1320h to 1530h",
          "venues": []
        },
        {
          "date": "23 May",
          "duration": "1430h to 1535h",
          "venues": []
        },
        {
          "date": "23 May",
          "duration": "1320h to 1530h",
          "venues": []
        }
      ],
      "name": "NTUC FairPrice",
      "address": "301 Yishun Avenue 2",
      "lon": "103.835058273602",
      "lat": "1.42951728655036",
      "id": "769093"
    },
    {
      "visits": [
        {
          "date": "26 May",
          "duration": "1710h to 1740h",
          "venues": []
        }
      ],
      "name": "Giant",
      "address": "256 Bangkit Road",
      "lon": "103.772937487128",
      "lat": "1.37904775583142",
      "id": "670256"
    },
    {
      "visits": [
        {
          "date": "26 May",
          "duration": "1850h to 2025h",
          "venues": []
        }
      ],
      "name": "Decathlon – Singapore Lab",
      "address": "230 Stadium Boulevard",
      "lon": "103.882367769241",
      "lat": "1.30426016123523",
      "id": "397799"
    },
    {
      "visits": [
        {
          "date": "26 May",
          "duration": "2100h to 2130h",
          "venues": []
        }
      ],
      "name": "Wenxintang Spa",
      "address": "316B Ang Mo Kio Street 31",
      "lon": "103.847677034369",
      "lat": "1.36462540270463",
      "id": "563316"
    },
    {
      "visits": [
        {
          "date": "26 May",
          "duration": "2115h to 2220h",
          "venues": []
        }
      ],
      "name": "People’s Park Centre",
      "address": "101 Upper Cross Street",
      "lon": "103.843922993246",
      "lat": "1.28560659056634",
      "id": "058357"
    },
    {
      "visits": [
        {
          "date": "27 to 31 May",
          "duration": "0000h to 2359h",
          "venues": []
        }
      ],
      "name": "Tuas Amenity Centre",
      "address": "71 Pioneer Road",
      "lon": "103.652208660421",
      "lat": "1.31720416812204",
      "id": "639591"
    },
    {
      "visits": [
        {
          "date": "27 May",
          "duration": "0750h to 0820h",
          "venues": []
        }
      ],
      "name": "Sheng Siong Supermarket",
      "address": "417 Fernvale Link",
      "lon": "103.879874611419",
      "lat": "1.39158622983505",
      "id": "790417"
    },
    {
      "visits": [
        {
          "date": "27 May",
          "duration": "0905h to 1030h",
          "venues": []
        }
      ],
      "name": "Bukit Merah Community Centre",
      "address": "4000 Jalan Bukit Merah",
      "lon": "103.815828547684",
      "lat": "1.28525427322707",
      "id": "159465"
    },
    {
      "visits": [
        {
          "date": "27 May",
          "duration": "0915h to 1400h",
          "venues": []
        }
      ],
      "name": "LeVel 33",
      "address": "8 Marina Boulevard",
      "lon": "103.854188393989",
      "lat": "1.27998145046295",
      "id": "018981"
    },
    {
      "visits": [
        {
          "date": "27 May",
          "duration": "0945h to 1100h",
          "venues": []
        }
      ],
      "name": "Jurong Port Pass/ Permit Office",
      "address": "37 Jurong Port Road",
      "lon": "103.722807330979",
      "lat": "1.3074595063712",
      "id": "619110"
    },
    {
      "visits": [
        {
          "date": "27 May",
          "duration": "1100h to 2230h",
          "venues": []
        }
      ],
      "name": "Chop Joo Hiong Eating House",
      "address": "237 Serangoon Avenue 3",
      "lon": "103.87013457465",
      "lat": "1.35381198342473",
      "id": "550237"
    },
    {
      "visits": [
        {
          "date": "27 May",
          "duration": "1125h to 1210h",
          "venues": []
        }
      ],
      "name": "United Square Shopping Mall",
      "address": "101 Thomson Road",
      "isNew": true,
      "lon": "103.843773665257",
      "lat": "1.31717838140911",
      "id": "307591"
    },
    {
      "visits": [
        {
          "date": "27 May",
          "duration": "1125h to 2035h",
          "venues": [
            "328 Katong Laksa"
          ]
        },
        {
          "date": "26 May",
          "duration": "1130h to 2100h",
          "venues": [
            "328 Katong Laksa"
          ]
        }
      ],
      "name": "Tiong Bahru Plaza",
      "address": "298 Tiong Bahru Road",
      "lon": "103.828004844701",
      "lat": "1.2863085351796",
      "id": "168730"
    },
    {
      "visits": [
        {
          "date": "27 May",
          "duration": "1240h to 1345h",
          "venues": []
        }
      ],
      "name": "NTUC FairPrice",
      "address": "50 Havelock Road",
      "lon": "103.826802915076",
      "lat": "1.2897647546758",
      "id": "160050"
    },
    {
      "visits": [
        {
          "date": "27 May",
          "duration": "1605h to 1810h",
          "venues": []
        }
      ],
      "name": "Health Management Centre",
      "address": "809 French Road",
      "lon": "103.862059784174",
      "lat": "1.3083939667367",
      "id": "200809"
    },
    {
      "visits": [
        {
          "date": "27 May",
          "duration": "1700h to 1730h",
          "venues": []
        }
      ],
      "name": "Sheng Siong Supermarket",
      "address": "200 Woodlands Industrial Park E7",
      "lon": "103.797050379065",
      "lat": "1.45089565555643",
      "id": "757177"
    },
    {
      "visits": [
        {
          "date": "27 May",
          "duration": "1725h to 1825h",
          "venues": []
        }
      ],
      "name": "GP Motoring",
      "address": "282 Macpherson Road",
      "lon": "103.877130417609",
      "lat": "1.33039834337195",
      "id": "348607"
    },
    {
      "visits": [
        {
          "date": "27 May",
          "duration": "1755h to 2030h",
          "venues": []
        }
      ],
      "name": "Lucky Plaza",
      "address": "304 Orchard Road",
      "lon": "103.834005158524",
      "lat": "1.3044637897474",
      "id": "238863"
    },
    {
      "visits": [
        {
          "date": "28 May",
          "duration": "0800h to 1800h",
          "venues": []
        }
      ],
      "name": "Orchard Hotel Singapore",
      "address": "442 Orchard Road",
      "lon": "103.828540491131",
      "lat": "1.3076228258502",
      "id": "238879"
    },
    {
      "visits": [
        {
          "date": "28 May",
          "duration": "1010h to 1155h",
          "venues": []
        }
      ],
      "name": "Carole Unisex Salon",
      "address": "620 Hougang Avenue 8",
      "lon": "103.883968140531",
      "lat": "1.3701440065551",
      "id": "530620"
    },
    {
      "visits": [
        {
          "date": "28 to 31 May",
          "duration": "1200h to 1900h",
          "venues": []
        },
        {
          "date": "27 May",
          "duration": "2230h to 2300h",
          "venues": []
        },
        {
          "date": "27 May",
          "duration": "1400h to 2200h",
          "venues": []
        }
      ],
      "name": "Atatcutz Singapore",
      "address": "348 Bedok Road",
      "lon": "103.948260304303",
      "lat": "1.33143623119911",
      "id": "469560"
    },
    {
      "visits": [
        {
          "date": "28 May",
          "duration": "1300h to 1340h",
          "venues": []
        }
      ],
      "name": "Masjid Jamek Queenstown",
      "address": "946 Margaret Drive",
      "lon": "103.815415725873",
      "lat": "1.29301045552152",
      "id": "149309"
    },
    {
      "visits": [
        {
          "date": "28 May",
          "duration": "1615h to 1650h",
          "venues": []
        },
        {
          "date": "25 May",
          "duration": "1535h to 1630h",
          "venues": []
        },
        {
          "date": "24 to 28 May",
          "duration": "0600h to 1900h",
          "venues": []
        }
      ],
      "name": "Sheng Siong Supermarket",
      "address": "455 Sengkang West Avenue",
      "lon": "103.871190376558",
      "lat": "1.39183688254074",
      "id": "790455"
    },
    {
      "visits": [
        {
          "date": "28 May",
          "duration": "1845h to 1935h",
          "venues": [
            "POPULAR Bookstore"
          ]
        },
        {
          "date": "28 May",
          "duration": "1830h to 2000h",
          "venues": []
        },
        {
          "date": "24 May",
          "duration": "2025h to 2100h",
          "venues": []
        }
      ],
      "name": "Causeway Point",
      "address": "1 Woodlands Square",
      "lon": "103.786009973678",
      "lat": "1.43608867729912",
      "id": "738099"
    },
    {
      "visits": [
        {
          "date": "28 May",
          "duration": "2015h to 2120h",
          "venues": [
            "NTUC FairPrice"
          ]
        }
      ],
      "name": "Woodlands Civic Centre",
      "address": "900 South Woodlands Drive",
      "lon": "103.786619615641",
      "lat": "1.4350778940091",
      "id": "730900"
    },
    {
      "visits": [
        {
          "date": "29 May",
          "duration": "1040h to 1140h",
          "venues": []
        },
        {
          "date": "26 May",
          "duration": "1040h to 1140h",
          "venues": []
        }
      ],
      "name": "Marsiling Lane Food Centre",
      "address": "20 Marsiling Lane",
      "lon": "103.776967080069",
      "lat": "1.44339444325539",
      "id": "730020"
    },
    {
      "visits": [
        {
          "date": "29 May",
          "duration": "1315h to 1500h",
          "venues": []
        }
      ],
      "name": "Chien Chi Tow Healthcare",
      "address": "78 Redhill Lane",
      "lon": "103.818486786844",
      "lat": "1.28843088346846",
      "id": "150078"
    },
    {
      "visits": [
        {
          "date": "29 May",
          "duration": "1555h to 1645h",
          "venues": []
        }
      ],
      "name": "Peninsula Plaza Singapore",
      "address": "111 North Bridge Road",
      "lon": "103.850804507292",
      "lat": "1.29232248414936",
      "id": "179098"
    },
    {
      "visits": [
        {
          "date": "29 May",
          "duration": "1815h to 1915h",
          "venues": []
        }
      ],
      "name": "Thong Sheng Motors Trading",
      "address": "7 Pioneer Road North",
      "lon": "103.695427890578",
      "lat": "1.32483634845564",
      "id": "628459"
    },
    {
      "visits": [
        {
          "date": "29 May",
          "duration": "1820h to 2000h",
          "venues": [
            "FairPrice Xtra"
          ]
        },
        {
          "date": "26 May",
          "duration": "1355h to 1700h",
          "venues": []
        }
      ],
      "name": "VivoCity",
      "address": "1 HarbourFront Walk",
      "lon": "103.821589247996",
      "lat": "1.26389581240004",
      "id": "098585"
    },
    {
      "visits": [
        {
          "date": "29 May",
          "duration": "1840h to 1950h",
          "venues": [
            "Decathlon"
          ]
        }
      ],
      "name": "ESR BizPark@Chai Chee",
      "address": "750A Chai Chee Road",
      "lon": "103.922124606113",
      "lat": "1.32297820248267",
      "id": "469001"
    },
    {
      "visits": [
        {
          "date": "29 to 30 May",
          "duration": "1930h to 0000h",
          "venues": []
        },
        {
          "date": "29 May",
          "duration": "0900h to 1300h",
          "venues": []
        },
        {
          "date": "29 May",
          "duration": "0600h to 1300h",
          "venues": []
        },
        {
          "date": "29 May",
          "duration": "0000h to 0730h",
          "venues": []
        },
        {
          "date": "28 May",
          "duration": "1930h to 0000h",
          "venues": []
        },
        {
          "date": "28 May",
          "duration": "0900h to 2100h",
          "venues": []
        },
        {
          "date": "27 May",
          "duration": "0900h to 2100h",
          "venues": []
        },
        {
          "date": "27 to 28 May",
          "duration": "0600h to 2100h",
          "venues": []
        },
        {
          "date": "27 May",
          "duration": "0000h to 0730h",
          "venues": []
        },
        {
          "date": "26 May",
          "duration": "0900h to 2100h",
          "venues": []
        },
        {
          "date": "26 to 27 May",
          "duration": "0900h to 1700h",
          "venues": []
        }
      ],
      "name": "NTUC Foodfare",
      "address": "308 Anchorvale Road",
      "lon": "103.886445107411",
      "lat": "1.38925397515391",
      "id": "540308"
    },
    {
      "visits": [
        {
          "date": "29 May",
          "duration": "2000h to 2035h",
          "venues": []
        }
      ],
      "name": "Prime Supermarket",
      "address": "763 Jurong West Street 75",
      "lon": "103.698292005963",
      "lat": "1.34872644269897",
      "id": "640763"
    },
    {
      "visits": [
        {
          "date": "29 May",
          "duration": "2030h to 2115h",
          "venues": []
        },
        {
          "date": "29 May",
          "duration": "2030h to 2055h",
          "venues": [
            "Cold Storage"
          ]
        }
      ],
      "name": "Plaza Singapura",
      "address": "68 Orchard Road",
      "lon": "103.845067272666",
      "lat": "1.30082071769235",
      "id": "238839"
    },
    {
      "visits": [
        {
          "date": "30 May",
          "duration": "1100h to 2200h",
          "venues": [
            "Pizza Hut"
          ]
        },
        {
          "date": "29 May",
          "duration": "0630h to 1300h",
          "venues": [
            "Fu Fa Food Court"
          ]
        },
        {
          "date": "28 May",
          "duration": "1100h to 2200h",
          "venues": [
            "Pizza Hut"
          ]
        },
        {
          "date": "27 to 28 May",
          "duration": "0630h to 2200h",
          "venues": [
            "Fu Fa Food Court"
          ]
        },
        {
          "date": "24 to 29 May",
          "duration": "1000h to 2200h",
          "venues": [
            "Fu Fa Food Court"
          ]
        }
      ],
      "name": "Hougang Green Shopping Mall",
      "address": "21 Hougang Street 51",
      "lon": "103.887847089168",
      "lat": "1.37931783471773",
      "id": "538719"
    },
    {
      "visits": [
        {
          "date": "30 May",
          "duration": "1125h to 1200h",
          "venues": []
        }
      ],
      "name": "Ang Mo Supermarket",
      "address": "642 Hougang Avenue 8",
      "lon": "103.879948293051",
      "lat": "1.37169878879802",
      "id": "530642"
    },
    {
      "visits": [
        {
          "date": "30 May",
          "duration": "1200h to 1300h",
          "venues": []
        }
      ],
      "name": "Bugis Street",
      "address": "3 New Bugis Street",
      "lon": "103.854935164999",
      "lat": "1.30056609522079",
      "id": "188867"
    },
    {
      "visits": [
        {
          "date": "30 May",
          "duration": "1800h to 1900h",
          "venues": []
        }
      ],
      "name": "Hong Yang Health Products & Foot Reflexology Centre",
      "address": "38 Beo Crescent",
      "lon": "103.827290023383",
      "lat": "1.28855393184563",
      "id": "160038"
    },
    {
      "visits": [
        {
          "date": "30 to 31 May",
          "duration": "2005h to 0005h",
          "venues": []
        },
        {
          "date": "29 May",
          "duration": "0110h to 0530h",
          "venues": []
        }
      ],
      "name": "Marina Bay Sands Casino",
      "address": "10 Bayfront Avenue",
      "lon": "103.858562162091",
      "lat": "1.28257452719678",
      "id": "018956"
    },
    {
      "visits": [
        {
          "date": "1 Jun",
          "duration": "1000h to 1230h",
          "venues": []
        }
      ],
      "name": "JIC Inspection Services",
      "address": "53 Pioneer Road",
      "lon": "103.657832233969",
      "lat": "1.31133149338762",
      "id": "628505"
    },
    {
      "visits": [
        {
          "date": "1 Jun",
          "duration": "1100h to 1230h",
          "venues": []
        }
      ],
      "name": "VICOM Inspection Centre",
      "address": "511 Bukit Batok Street 2",
      "lon": "103.755832339467",
      "lat": "1.34175978313366",
      "id": "659545"
    },
    {
      "visits": [
        {
          "date": "1 Jun",
          "duration": "1955h to 2030h",
          "venues": [
            "NTUC FairPrice"
          ]
        },
        {
          "date": "29 May",
          "duration": "1020h to 1100h",
          "venues": []
        },
        {
          "date": "28 May",
          "duration": "1955h to 2055h",
          "venues": [
            "NTUC FairPrice"
          ]
        }
      ],
      "name": "Seletar Mall",
      "address": "33 Sengkang West Avenue",
      "lon": "103.876156956828",
      "lat": "1.3913688093851",
      "id": "797653"
    }
  ],
  "timestamp": 1623031447871
}